reliable_queue/__init__.py
reliable_queue-0.0.10.dist-info/LICENSE
reliable_queue-0.0.10.dist-info/METADATA
reliable_queue-0.0.10.dist-info/WHEEL
reliable_queue-0.0.10.dist-info/top_level.txt
reliable_queue-0.0.10.dist-info/RECORD
