Metadata-Version: 2.1
Name: reliable-queue
Version: 0.0.10
Summary: A reliable queue for the Manycore-Mail project
Author-email: Nicolas Toper <ntoper@manycore.io>, Marcus Engene <marcus@manycore.io>
Maintainer-email: Nicolas Toper <ntoper@manycore.io>, Marcus Engene <marcus@manycore.io>
Project-URL: Homepage, https://github.com/manycore-com/Manycore-ReliableQueue
Project-URL: Bug Tracker, https://github.com/manycore-com/Manycore-ReliableQueue/issues
Classifier: Programming Language :: Python :: 3
Classifier: License :: OSI Approved :: MIT License
Classifier: Operating System :: OS Independent
Requires-Python: >=3.7
License-File: LICENSE
Requires-Dist: redis (>=4.3.5)
